{
  "/etc/issue.net": "Ubuntu 20.04.5 LTS",
  "commandLine": [
    "/usr/bin/fdroid update"
  ],
  "fdroiddata": {
    "commitId": "7d1c07240075bf7faef2088add9454cc9478d77d",
    "isDirty": true,
    "modifiedFiles": [
      "repo/index-v1.jar",
      "repo/index-v1.json",
      "repo/index.jar",
      "repo/index.xml",
      "repo/smarttube_beta.apk",
      "repo/status/running.json",
      "repo/status/update.json"
    ],
    "untrackedFiles": []
  },
  "startTimestamp": 1672012828000,
  "subcommand": "update"
}