{
  "/etc/issue.net": "Ubuntu 20.04.5 LTS",
  "commandLine": [
    "/usr/bin/fdroid update"
  ],
  "fdroiddata": {
    "commitId": "dee7bc1e8e8732b52fc7adedba804b5927d6f29e",
    "isDirty": true,
    "modifiedFiles": [
      "repo/index-v1.jar",
      "repo/index-v1.json",
      "repo/index.jar",
      "repo/index.xml",
      "repo/smarttube_beta.apk",
      "repo/status/running.json",
      "repo/status/update.json"
    ],
    "untrackedFiles": []
  },
  "startTimestamp": 1675382424000,
  "subcommand": "update"
}