{
  "/etc/issue.net": "Ubuntu 20.04.4 LTS",
  "commandLine": [
    "/usr/bin/fdroid update"
  ],
  "fdroiddata": {
    "commitId": "509f86595ff8689bc516fcec3338fedfc1ef77b5",
    "isDirty": true,
    "modifiedFiles": [
      "repo/Installer-release.apk",
      "repo/app-release.apk",
      "repo/index-v1.jar",
      "repo/index-v1.json",
      "repo/index.html",
      "repo/index.jar",
      "repo/index.xml",
      "repo/magisk-canary.apk",
      "repo/reddit-universal.apk",
      "repo/smarttube_beta.apk",
      "repo/smarttube_stable.apk",
      "repo/status/running.json",
      "repo/status/update.json",
      "repo/xManager.apk"
    ],
    "untrackedFiles": []
  },
  "startTimestamp": 1658880912000,
  "subcommand": "update"
}